django_boost/__init__.py
django_boost/apps.py
django_boost/checks.py
django_boost/context_processors.py
django_boost/shortcuts.py
django_boost/validators.py
django_boost/admin/__init__.py
django_boost/admin/actions.py
django_boost/admin/filters.py
django_boost/admin/mixins.py
django_boost/admin/sites.py
django_boost/admin_tools/__init__.py
django_boost/admin_tools/apps.py
django_boost/admin_tools/management/__init__.py
django_boost/admin_tools/management/commands/__init__.py
django_boost/admin_tools/management/commands/listsuperuser.py
django_boost/conf/app_template/__init__.py-tpl
django_boost/conf/app_template/admin.py-tpl
django_boost/conf/app_template/apps.py-tpl
django_boost/conf/app_template/forms.py-tpl
django_boost/conf/app_template/models.py-tpl
django_boost/conf/app_template/tests.py-tpl
django_boost/conf/app_template/urls.py-tpl
django_boost/conf/app_template/views.py-tpl
django_boost/conf/app_template/migrations/__init__.py-tpl
django_boost/core/__init__.py
django_boost/core/management.py
django_boost/db/__init__.py
django_boost/db/router.py
django_boost/forms/__init__.py
django_boost/forms/fields.py
django_boost/forms/mixins.py
django_boost/forms/widgets.py
django_boost/http/__init__.py
django_boost/http/response.py
django_boost/locale/af/LC_MESSAGES/django.mo
django_boost/locale/af/LC_MESSAGES/django.po
django_boost/locale/ar/LC_MESSAGES/django.mo
django_boost/locale/ar/LC_MESSAGES/django.po
django_boost/locale/ast/LC_MESSAGES/django.mo
django_boost/locale/ast/LC_MESSAGES/django.po
django_boost/locale/az/LC_MESSAGES/django.mo
django_boost/locale/az/LC_MESSAGES/django.po
django_boost/locale/be/LC_MESSAGES/django.mo
django_boost/locale/be/LC_MESSAGES/django.po
django_boost/locale/bg/LC_MESSAGES/django.mo
django_boost/locale/bg/LC_MESSAGES/django.po
django_boost/locale/bn/LC_MESSAGES/django.mo
django_boost/locale/bn/LC_MESSAGES/django.po
django_boost/locale/br/LC_MESSAGES/django.mo
django_boost/locale/br/LC_MESSAGES/django.po
django_boost-2.1.dist-info/LICENSE
django_boost-2.1.dist-info/METADATA
django_boost-2.1.dist-info/WHEEL
django_boost-2.1.dist-info/top_level.txt
django_boost-2.1.dist-info/RECORD
