Metadata-Version: 2.1
Name: django-boost
Version: 2.1
Summary: Django Extension library
Home-page: https://github.com/ChanTsune/Django-Boost
Author: ChanTsune
Author-email: yshegou@gmail.com
License: MIT
Keywords: django extension
Platform: any
Classifier: Programming Language :: Python
Classifier: Programming Language :: Python :: 3
Classifier: Programming Language :: Python :: 3.8
Classifier: Programming Language :: Python :: 3.9
Classifier: Programming Language :: Python :: 3.10
Classifier: Framework :: Django
Classifier: Framework :: Django :: 3.0
Classifier: Framework :: Django :: 3.1
Classifier: Framework :: Django :: 3.2
Classifier: Framework :: Django :: 4.0
Classifier: License :: OSI Approved :: MIT License
License-File: LICENSE
Requires-Dist: Django (>=3.0)
Requires-Dist: user-agents (>=2.0)
